{
  "updated_at": "2026-03-26 14:18 UTC",
  "data": [
    {
      "Ticker": "VUG",
      "Preço Atual": 440.95,
      "Média 200d": 450.52,
      "Distância MM (%)": -2.12,
      "Distância Topo (%)": -12.47,
      "CAGR 5y (%)": 12.21,
      "Max Drawdown (%)": -35.61,
      "Volatilidade (%)": 22.11,
      "Sinal": "MANTER"
    },
    {
      "Ticker": "SCHD",
      "Preço Atual": 30.77,
      "Média 200d": 27.3,
      "Distância MM (%)": 12.71,
      "Distância Topo (%)": -3.41,
      "CAGR 5y (%)": 8.25,
      "Max Drawdown (%)": -16.84,
      "Volatilidade (%)": 14.4,
      "Sinal": "REDUZIR"
    },
    {
      "Ticker": "IVV",
      "Preço Atual": 657.42,
      "Média 200d": 639.46,
      "Distância MM (%)": 2.81,
      "Distância Topo (%)": -5.66,
      "CAGR 5y (%)": 12.2,
      "Max Drawdown (%)": -24.53,
      "Volatilidade (%)": 16.8,
      "Sinal": "MANTER"
    },
    {
      "Ticker": "QQQ",
      "Preço Atual": 583.93,
      "Média 200d": 570.58,
      "Distância MM (%)": 2.34,
      "Distância Topo (%)": -8.04,
      "CAGR 5y (%)": 13.77,
      "Max Drawdown (%)": -35.12,
      "Volatilidade (%)": 22.3,
      "Sinal": "MANTER"
    },
    {
      "Ticker": "XLK",
      "Preço Atual": 135.27,
      "Média 200d": 131.59,
      "Distância MM (%)": 2.8,
      "Distância Topo (%)": -10.91,
      "CAGR 5y (%)": 16.23,
      "Max Drawdown (%)": -33.56,
      "Volatilidade (%)": 24.6,
      "Sinal": "MANTER"
    },
    {
      "Ticker": "IYW",
      "Preço Atual": 183.91,
      "Média 200d": 181.37,
      "Distância MM (%)": 1.4,
      "Distância Topo (%)": -12.89,
      "CAGR 5y (%)": 16.6,
      "Max Drawdown (%)": -39.44,
      "Volatilidade (%)": 25.66,
      "Sinal": "MANTER"
    },
    {
      "Ticker": "MAGS",
      "Preço Atual": 58.43,
      "Média 200d": 58.71,
      "Distância MM (%)": -0.47,
      "Distância Topo (%)": -14.15,
      "CAGR 5y (%)": 35.57,
      "Max Drawdown (%)": -29.91,
      "Volatilidade (%)": 26.09,
      "Sinal": "MANTER"
    },
    {
      "Ticker": "BOVA11",
      "Preço Atual": 180.96,
      "Média 200d": 147.27,
      "Distância MM (%)": 22.87,
      "Distância Topo (%)": -3.63,
      "CAGR 5y (%)": 10.52,
      "Max Drawdown (%)": -26.4,
      "Volatilidade (%)": 18.09,
      "Sinal": "REDUZIR"
    }
  ]
}